sql_tools/__init__.py
sql_tools/constants.py
sql_tools/exception.py
sql_tools/internals.py
sql_tools/mysql/__init__.py
sql_tools/mysql/connect.py
sql_tools/mysql/dbTools.py
sql_tools/mysql/execute.py
sql_tools/mysql/tableTools.py
sql_tools/mysql/driver/__init__.py
sql_tools/mysql/driver/_auth.py
sql_tools/mysql/driver/_compat.py
sql_tools/mysql/driver/_socketio.py
sql_tools/mysql/driver/charset.py
sql_tools/mysql/driver/connections.py
sql_tools/mysql/driver/converters.py
sql_tools/mysql/driver/cursors.py
sql_tools/mysql/driver/err.py
sql_tools/mysql/driver/optionfile.py
sql_tools/mysql/driver/protocol.py
sql_tools/mysql/driver/times.py
sql_tools/mysql/driver/util.py
sql_tools/mysql/driver/constants/CLIENT.py
sql_tools/mysql/driver/constants/COMMAND.py
sql_tools/mysql/driver/constants/CR.py
sql_tools/mysql/driver/constants/ER.py
sql_tools/mysql/driver/constants/FIELD_TYPE.py
sql_tools/mysql/driver/constants/FLAG.py
sql_tools/mysql/driver/constants/SERVER_STATUS.py
sql_tools/mysql/driver/constants/__init__.py
sql_tools/sqlite/__init__.py
sql_tools/sqlite/advTools.py
sql_tools/sqlite/connect.py
sql_tools/sqlite/dbTools.py
sql_tools/sqlite/execute.py
sql_tools/sqlite/io.py
sql_tools/sqlite/sampleData.py
sql_tools/sqlite/tableTools.py
sql_tools/sqlite/command/__init__.py
sql_tools/sqlite/command/parse.py
sql_tools/sqlite/driver/__init__.py
sql_tools/sqlite/driver/dbapi2.py
sql_tools/sqlite/driver/dump.py
sql_tools/tools/__init__.py
sql_tools/tools/boost.py
sql_tools/tools/fetchDb.py
sql_tools-3.1.0.dist-info/LICENSE
sql_tools-3.1.0.dist-info/METADATA
sql_tools-3.1.0.dist-info/WHEEL
sql_tools-3.1.0.dist-info/top_level.txt
sql_tools-3.1.0.dist-info/RECORD
