Metadata-Version: 2.1
Name: sql-tools
Version: 3.1.0
Summary: An integrative library that contains tools for performing various tasks related to MySQL/sqlite3 databases.
Home-page: https://github.com/yogesh-aggarwal/sql-tools-lib
Author: Yogesh Aggarwal
Author-email: developeryogeshgit@gmail.com
License: AGPL 3.0
Download-URL: https://raw.githubusercontent.com/yogesh-aggarwal/sql-tools-lib/master/dist/sql_tools-3.1.0.tar.gz
Keywords: SQL,DATABASES,TABLES,RECORDS
Platform: UNKNOWN
Classifier: Development Status :: 5 - Production/Stable
Classifier: Intended Audience :: Developers
Classifier: Programming Language :: Python :: 3
Classifier: Programming Language :: Python :: 3.4
Classifier: Programming Language :: Python :: 3.5
Classifier: Programming Language :: Python :: 3.6
Classifier: Programming Language :: Python :: 3.7
Classifier: Programming Language :: Python :: 3.8
Requires-Dist: numpy
Requires-Dist: pandas
Requires-Dist: cryptography
Requires-Dist: colorama
